[{"timestamp":"2023-10-19T15:44:05.656Z","count":0,"uniques":0},{"timestamp":"2023-10-20T23:34:46.083Z","count":0,"uniques":0},{"timestamp":"2023-10-21T23:35:03.230Z","count":0,"uniques":0},{"timestamp":"2023-10-22T23:34:57.134Z","count":0,"uniques":0},{"timestamp":"2023-10-23T23:35:11.463Z","count":0,"uniques":0},{"timestamp":"2023-10-24T23:35:04.793Z","count":0,"uniques":0},{"timestamp":"2023-10-25T23:35:20.952Z","count":0,"uniques":0},{"timestamp":"2023-10-26T23:35:16.170Z","count":0,"uniques":0}]
