[{"timestamp":"2024-03-14T23:36:13.705Z","count":0,"uniques":0},{"timestamp":"2024-03-15T23:34:44.765Z","count":0,"uniques":0},{"timestamp":"2024-03-16T23:35:42.075Z","count":0,"uniques":0},{"timestamp":"2024-03-17T23:35:20.472Z","count":0,"uniques":0},{"timestamp":"2024-03-18T23:34:51.730Z","count":0,"uniques":0},{"timestamp":"2024-03-19T23:35:01.488Z","count":0,"uniques":0},{"timestamp":"2024-03-20T23:34:52.512Z","count":0,"uniques":0},{"timestamp":"2024-03-21T23:34:19.506Z","count":0,"uniques":0}]
