[{"timestamp":"2025-04-13T01:57:38.237Z","count":0,"uniques":0},{"timestamp":"2025-04-14T23:37:26.776Z","count":0,"uniques":0},{"timestamp":"2025-04-15T23:37:39.978Z","count":0,"uniques":0},{"timestamp":"2025-04-16T23:38:04.177Z","count":0,"uniques":0},{"timestamp":"2025-04-17T23:38:05.607Z","count":0,"uniques":0},{"timestamp":"2025-04-18T23:37:58.443Z","count":0,"uniques":0},{"timestamp":"2025-04-19T23:37:25.554Z","count":0,"uniques":0},{"timestamp":"2025-04-20T23:36:36.435Z","count":0,"uniques":0}]
