[{"timestamp":"2024-11-08T23:36:59.346Z","count":0,"uniques":0},{"timestamp":"2024-11-09T23:37:35.715Z","count":0,"uniques":0},{"timestamp":"2024-11-10T23:36:57.379Z","count":0,"uniques":0},{"timestamp":"2024-11-11T23:37:21.450Z","count":0,"uniques":0},{"timestamp":"2024-11-12T23:37:33.580Z","count":0,"uniques":0},{"timestamp":"2024-11-13T23:38:50.791Z","count":0,"uniques":0},{"timestamp":"2024-11-14T23:39:02.355Z","count":0,"uniques":0},{"timestamp":"2024-11-15T23:38:18.790Z","count":0,"uniques":0}]
