[{"timestamp":"2024-11-11T23:37:21.450Z","count":0,"uniques":0},{"timestamp":"2024-11-12T23:37:33.580Z","count":0,"uniques":0},{"timestamp":"2024-11-13T23:38:50.791Z","count":0,"uniques":0},{"timestamp":"2024-11-14T23:39:02.355Z","count":0,"uniques":0},{"timestamp":"2024-11-15T23:38:18.790Z","count":0,"uniques":0},{"timestamp":"2024-11-16T23:38:38.368Z","count":0,"uniques":0},{"timestamp":"2024-11-17T23:38:54.883Z","count":0,"uniques":0},{"timestamp":"2024-11-18T23:38:15.919Z","count":0,"uniques":0}]
