[{"timestamp":"2025-06-29T23:42:02.560Z","count":0,"uniques":0},{"timestamp":"2025-06-30T23:42:18.619Z","count":0,"uniques":0},{"timestamp":"2025-07-01T23:42:25.043Z","count":0,"uniques":0},{"timestamp":"2025-07-02T23:43:31.415Z","count":0,"uniques":0},{"timestamp":"2025-07-03T23:42:45.300Z","count":0,"uniques":0},{"timestamp":"2025-07-04T23:42:07.786Z","count":0,"uniques":0},{"timestamp":"2025-07-05T23:42:36.481Z","count":0,"uniques":0},{"timestamp":"2025-07-06T23:43:17.328Z","count":0,"uniques":0}]
