[{"timestamp":"2024-11-13T23:39:55.985Z","count":0,"uniques":0},{"timestamp":"2024-11-14T23:40:15.286Z","count":0,"uniques":0},{"timestamp":"2024-11-15T23:39:30.216Z","count":0,"uniques":0},{"timestamp":"2024-11-16T23:39:49.515Z","count":0,"uniques":0},{"timestamp":"2024-11-17T23:40:07.066Z","count":0,"uniques":0},{"timestamp":"2024-11-18T23:39:17.802Z","count":0,"uniques":0},{"timestamp":"2024-11-19T23:39:41.993Z","count":0,"uniques":0},{"timestamp":"2024-11-20T23:39:17.624Z","count":0,"uniques":0}]
