[{"timestamp":"2025-05-06T23:39:49.528Z","count":0,"uniques":0},{"timestamp":"2025-05-07T23:41:44.750Z","count":0,"uniques":0},{"timestamp":"2025-05-08T23:41:15.981Z","count":0,"uniques":0},{"timestamp":"2025-05-09T23:39:09.978Z","count":0,"uniques":0},{"timestamp":"2025-05-10T23:38:39.987Z","count":0,"uniques":0},{"timestamp":"2025-05-11T23:38:57.327Z","count":0,"uniques":0},{"timestamp":"2025-05-12T23:41:06.992Z","count":0,"uniques":0},{"timestamp":"2025-05-13T23:39:55.469Z","count":0,"uniques":0},{"timestamp":"2025-05-14T23:40:46.892Z","count":0,"uniques":0},{"timestamp":"2025-05-15T23:40:46.288Z","count":0,"uniques":0},{"timestamp":"2025-05-16T23:39:39.957Z","count":0,"uniques":0},{"timestamp":"2025-05-17T23:39:09.412Z","count":0,"uniques":0},{"timestamp":"2025-05-18T23:39:52.560Z","count":0,"uniques":0},{"timestamp":"2025-05-19T23:40:26.857Z","count":0,"uniques":0},{"timestamp":"2025-05-20T23:39:38.555Z","count":0,"uniques":0},{"timestamp":"2025-05-21T23:40:07.260Z","count":0,"uniques":0},{"timestamp":"2025-05-22T23:40:09.405Z","count":0,"uniques":0},{"timestamp":"2025-05-23T23:41:29.995Z","count":0,"uniques":0},{"timestamp":"2025-05-24T23:39:28.649Z","count":0,"uniques":0},{"timestamp":"2025-05-25T23:39:44.659Z","count":0,"uniques":0},{"timestamp":"2025-05-26T23:41:01.709Z","count":0,"uniques":0},{"timestamp":"2025-05-27T23:39:46.357Z","count":0,"uniques":0},{"timestamp":"2025-05-28T23:40:15.434Z","count":0,"uniques":0},{"timestamp":"2025-05-29T23:40:17.818Z","count":0,"uniques":0},{"timestamp":"2025-05-30T23:40:17.818Z","count":0,"uniques":0},{"timestamp":"2025-05-31T23:40:25.106Z","count":0,"uniques":0},{"timestamp":"2025-06-01T23:40:05.335Z","count":0,"uniques":0},{"timestamp":"2025-06-02T23:42:04.339Z","count":0,"uniques":0},{"timestamp":"2025-06-03T23:40:57.735Z","count":0,"uniques":0},{"timestamp":"2025-06-04T23:40:50.759Z","count":0,"uniques":0},{"timestamp":"2025-06-05T23:43:36.729Z","count":0,"uniques":0}]
