[{"timestamp":"2024-06-23T23:36:56.713Z","count":0,"uniques":0},{"timestamp":"2024-06-24T23:36:54.587Z","count":0,"uniques":0},{"timestamp":"2024-06-25T23:36:50.649Z","count":0,"uniques":0},{"timestamp":"2024-06-26T23:37:15.328Z","count":0,"uniques":0},{"timestamp":"2024-06-27T23:36:15.951Z","count":0,"uniques":0},{"timestamp":"2024-06-28T23:37:02.362Z","count":0,"uniques":0},{"timestamp":"2024-06-29T23:37:39.941Z","count":0,"uniques":0},{"timestamp":"2024-06-30T23:36:35.790Z","count":0,"uniques":0}]
