[{"timestamp":"2025-05-01T23:39:00.779Z","count":0,"uniques":0},{"timestamp":"2025-05-02T23:38:42.389Z","count":0,"uniques":0},{"timestamp":"2025-05-03T23:37:50.178Z","count":0,"uniques":0},{"timestamp":"2025-05-04T23:38:12.432Z","count":0,"uniques":0},{"timestamp":"2025-05-05T23:40:28.951Z","count":0,"uniques":0},{"timestamp":"2025-05-06T23:38:46.833Z","count":0,"uniques":0},{"timestamp":"2025-05-07T23:40:39.628Z","count":0,"uniques":0},{"timestamp":"2025-05-08T00:00:00.000Z","count":1,"uniques":1}]
