[{"timestamp":"2024-08-02T16:58:56.355Z","count":0,"uniques":0},{"timestamp":"2024-08-03T16:58:56.355Z","count":0,"uniques":0},{"timestamp":"2024-08-04T18:25:27.650Z","count":0,"uniques":0},{"timestamp":"2024-08-05T00:00:00.000Z","count":15,"uniques":2},{"timestamp":"2024-08-06T23:34:49.068Z","count":0,"uniques":0},{"timestamp":"2024-08-07T23:34:52.241Z","count":0,"uniques":0},{"timestamp":"2024-08-08T23:34:38.744Z","count":0,"uniques":0},{"timestamp":"2024-08-09T23:34:38.496Z","count":0,"uniques":0}]
