[{"timestamp":"2024-12-04T23:40:27.943Z","count":0,"uniques":0},{"timestamp":"2024-12-05T23:40:32.264Z","count":0,"uniques":0},{"timestamp":"2024-12-06T23:40:04.696Z","count":0,"uniques":0},{"timestamp":"2024-12-07T23:39:38.714Z","count":0,"uniques":0},{"timestamp":"2024-12-08T23:39:02.067Z","count":0,"uniques":0},{"timestamp":"2024-12-09T23:40:53.592Z","count":0,"uniques":0},{"timestamp":"2024-12-10T23:40:19.735Z","count":0,"uniques":0},{"timestamp":"2024-12-11T23:40:36.358Z","count":0,"uniques":0}]
