[{"timestamp":"2025-07-26T23:43:18.862Z","count":0,"uniques":0},{"timestamp":"2025-07-27T23:44:41.236Z","count":0,"uniques":0},{"timestamp":"2025-07-28T23:46:36.166Z","count":0,"uniques":0},{"timestamp":"2025-07-29T23:45:13.689Z","count":0,"uniques":0},{"timestamp":"2025-07-30T23:46:05.306Z","count":0,"uniques":0},{"timestamp":"2025-07-31T23:44:08.415Z","count":0,"uniques":0},{"timestamp":"2025-08-01T23:44:27.254Z","count":0,"uniques":0},{"timestamp":"2025-08-02T23:46:39.556Z","count":0,"uniques":0}]
