[{"timestamp":"2023-11-17T23:36:00.451Z","count":0,"uniques":0},{"timestamp":"2023-11-18T23:35:45.497Z","count":0,"uniques":0},{"timestamp":"2023-11-19T23:36:07.710Z","count":0,"uniques":0},{"timestamp":"2023-11-20T23:36:25.823Z","count":0,"uniques":0},{"timestamp":"2023-11-21T23:36:32.671Z","count":0,"uniques":0},{"timestamp":"2023-11-22T23:36:02.345Z","count":0,"uniques":0},{"timestamp":"2023-11-23T23:35:53.048Z","count":0,"uniques":0},{"timestamp":"2023-11-24T23:35:46.304Z","count":0,"uniques":0}]
