[{"timestamp":"2025-04-14T23:37:47.714Z","count":0,"uniques":0},{"timestamp":"2025-04-15T23:38:01.114Z","count":0,"uniques":0},{"timestamp":"2025-04-16T23:38:26.696Z","count":0,"uniques":0},{"timestamp":"2025-04-17T23:38:26.724Z","count":0,"uniques":0},{"timestamp":"2025-04-18T23:38:21.709Z","count":0,"uniques":0},{"timestamp":"2025-04-19T23:37:46.736Z","count":0,"uniques":0},{"timestamp":"2025-04-20T23:36:56.748Z","count":0,"uniques":0},{"timestamp":"2025-04-21T23:37:52.429Z","count":0,"uniques":0}]
