[{"timestamp":"2025-01-26T00:00:00.000Z","count":29,"uniques":1},{"timestamp":"2025-01-27T16:10:16.507Z","count":0,"uniques":0},{"timestamp":"2025-01-28T16:10:16.507Z","count":0,"uniques":0},{"timestamp":"2025-01-29T16:10:16.507Z","count":0,"uniques":0},{"timestamp":"2025-01-30T16:10:16.507Z","count":0,"uniques":0},{"timestamp":"2025-01-31T16:10:16.507Z","count":0,"uniques":0},{"timestamp":"2025-02-01T16:10:16.507Z","count":0,"uniques":0},{"timestamp":"2025-02-02T23:36:30.405Z","count":0,"uniques":0}]
