[{"timestamp":"2024-09-01T23:37:22.515Z","count":0,"uniques":0},{"timestamp":"2024-09-02T23:37:24.302Z","count":0,"uniques":0},{"timestamp":"2024-09-03T23:36:37.242Z","count":0,"uniques":0},{"timestamp":"2024-09-04T23:36:23.250Z","count":0,"uniques":0},{"timestamp":"2024-09-05T23:36:29.526Z","count":0,"uniques":0},{"timestamp":"2024-09-06T23:37:42.232Z","count":0,"uniques":0},{"timestamp":"2024-09-07T23:37:33.094Z","count":0,"uniques":0},{"timestamp":"2024-09-08T23:36:30.518Z","count":0,"uniques":0}]
