[{"timestamp":"2025-04-08T23:38:34.698Z","count":0,"uniques":0},{"timestamp":"2025-04-09T23:38:20.605Z","count":0,"uniques":0},{"timestamp":"2025-04-10T23:39:11.914Z","count":0,"uniques":0},{"timestamp":"2025-04-11T01:59:01.871Z","count":0,"uniques":0},{"timestamp":"2025-04-12T01:59:01.871Z","count":0,"uniques":0},{"timestamp":"2025-04-13T01:59:01.871Z","count":0,"uniques":0},{"timestamp":"2025-04-14T23:38:50.771Z","count":0,"uniques":0},{"timestamp":"2025-04-15T23:39:05.304Z","count":0,"uniques":0},{"timestamp":"2025-04-16T23:39:34.006Z","count":0,"uniques":0},{"timestamp":"2025-04-17T23:39:29.542Z","count":0,"uniques":0},{"timestamp":"2025-04-18T23:39:31.295Z","count":0,"uniques":0},{"timestamp":"2025-04-19T23:38:50.123Z","count":0,"uniques":0},{"timestamp":"2025-04-20T23:37:57.414Z","count":0,"uniques":0},{"timestamp":"2025-04-21T23:38:55.086Z","count":0,"uniques":0},{"timestamp":"2025-04-22T23:39:48.700Z","count":0,"uniques":0},{"timestamp":"2025-04-23T23:39:13.436Z","count":0,"uniques":0},{"timestamp":"2025-04-24T23:38:43.746Z","count":0,"uniques":0},{"timestamp":"2025-04-25T23:39:02.061Z","count":0,"uniques":0},{"timestamp":"2025-04-26T23:38:45.897Z","count":0,"uniques":0},{"timestamp":"2025-04-27T23:39:38.837Z","count":0,"uniques":0},{"timestamp":"2025-04-28T23:39:36.237Z","count":0,"uniques":0},{"timestamp":"2025-04-29T23:39:09.526Z","count":0,"uniques":0},{"timestamp":"2025-04-30T23:40:03.734Z","count":0,"uniques":0},{"timestamp":"2025-05-01T23:39:45.104Z","count":0,"uniques":0},{"timestamp":"2025-05-02T23:39:24.655Z","count":0,"uniques":0},{"timestamp":"2025-05-03T23:38:32.173Z","count":0,"uniques":0},{"timestamp":"2025-05-04T23:38:58.927Z","count":0,"uniques":0},{"timestamp":"2025-05-05T23:41:14.609Z","count":0,"uniques":0},{"timestamp":"2025-05-06T23:39:28.779Z","count":0,"uniques":0},{"timestamp":"2025-05-07T23:41:23.065Z","count":0,"uniques":0},{"timestamp":"2025-05-08T23:40:52.325Z","count":0,"uniques":0}]
